NOTICE
superlinked/evaluation/__init__.py
superlinked/evaluation/charts/__init__.py
superlinked/evaluation/charts/recency_plotter.py
superlinked/evaluation/dag_displayer/__init__.py
superlinked/evaluation/dag_displayer/dag_displayer.py
superlinked/evaluation/pandas_converter.py
superlinked/evaluation/storage_usage/__init__.py
superlinked/evaluation/storage_usage/data_stream_observer.py
superlinked/evaluation/storage_usage/storage_usage_evaluator.py
superlinked/evaluation/storage_usage/storage_usage_report.py
superlinked/evaluation/storage_usage/vdb_watcher.py
superlinked/evaluation/vector_sampler.py
superlinked/framework/__init__.py
superlinked/framework/blob/__init__.py
superlinked/framework/blob/blob_handler.py
superlinked/framework/blob/blob_handler_factory.py
superlinked/framework/blob/blob_id_generator.py
superlinked/framework/blob/blob_metadata.py
superlinked/framework/blob/gcs_blob_handler.py
superlinked/framework/common/__init__.py
superlinked/framework/common/calculation/__init__.py
superlinked/framework/common/calculation/distance_metric.py
superlinked/framework/common/calculation/vector_similarity.py
superlinked/framework/common/const.py
superlinked/framework/common/dag/__init__.py
superlinked/framework/common/dag/aggregation_node.py
superlinked/framework/common/dag/categorical_similarity_node.py
superlinked/framework/common/dag/chunking_node.py
superlinked/framework/common/dag/comparison_filter_node.py
superlinked/framework/common/dag/concatenation_node.py
superlinked/framework/common/dag/constant_node.py
superlinked/framework/common/dag/context.py
superlinked/framework/common/dag/custom_node.py
superlinked/framework/common/dag/dag.py
superlinked/framework/common/dag/dag_effect.py
superlinked/framework/common/dag/effect_modifier.py
superlinked/framework/common/dag/embedding_node.py
superlinked/framework/common/dag/event_aggregation_node.py
superlinked/framework/common/dag/image_embedding_node.py
superlinked/framework/common/dag/index_node.py
superlinked-37.5.0.dist-info/LICENSE
superlinked-37.5.0.dist-info/METADATA
superlinked-37.5.0.dist-info/NOTICE
superlinked-37.5.0.dist-info/WHEEL
superlinked-37.5.0.dist-info/RECORD
