Metadata-Version: 2.1
Name: superlinked
Version: 37.5.0
Summary: The Superlinked vector computing library
License: Apache-2.0
Author: Superlinked Release
Author-email: release@superlinked.com
Requires-Python: >=3.10,<3.13
Classifier: License :: OSI Approved :: Apache Software License
Classifier: Programming Language :: Python :: 3
Classifier: Programming Language :: Python :: 3.10
Classifier: Programming Language :: Python :: 3.11
Classifier: Programming Language :: Python :: 3.12
Provides-Extra: batch
Provides-Extra: interactive
Provides-Extra: mongo
Provides-Extra: pub-sub
Provides-Extra: qdrant
Provides-Extra: redis
Provides-Extra: storage
Provides-Extra: topk
Requires-Dist: Deprecated (>=1.2.18,<2.0.0)
Requires-Dist: accelerate (>=0.26.0) ; extra == "interactive"
Requires-Dist: aiofiles (>=24.1.0,<25.0.0)
Requires-Dist: altair (==5.2.0) ; extra == "interactive"
Requires-Dist: asgi-correlation-id (>=4.3.4,<5.0.0)
Requires-Dist: beartype (>=0.17.2,<0.22.0)
Requires-Dist: cachetools (>=5.4,<6.0)
Requires-Dist: filelock (>=3.16.1,<4.0.0)
Requires-Dist: furl (>=2.1.3,<3.0.0)
Requires-Dist: google-cloud-pubsub (>=2.23.0,<3.0.0) ; extra == "pub-sub"
Requires-Dist: google-cloud-storage (>=2.18.2,<4.0.0) ; extra == "storage"
Requires-Dist: graphviz (>=0.20.1,<0.22.0)
Requires-Dist: httpx (>=0.28.1,<0.29.0)
Requires-Dist: instructor (>=1.11.3,<2.0.0)
Requires-Dist: ipywidgets (>=8.1.2,<9.0.0) ; extra == "interactive"
Requires-Dist: jinja2 (>=3.1.4,<4.0.0)
Requires-Dist: jupyter (>=1.0.0,<2.0.0) ; extra == "interactive"
Requires-Dist: modal (==1.1.3)
Requires-Dist: mongo-types (>=0.15.1,<0.16.0) ; extra == "mongo"
Requires-Dist: nest-asyncio (>=1.6.0,<2.0.0)
Requires-Dist: numpy (>=1.25.2,<=3.0.0)
Requires-Dist: open_clip_torch (>=3.0.0,<4.0.0)
Requires-Dist: opentelemetry-api (>=1.34.1,<2.0.0)
Requires-Dist: opentelemetry-sdk (>=1.34.1,<2.0.0)
Requires-Dist: pandas (>=2.0.3,<3.0.0)
Requires-Dist: pydantic (>=2.6.4,<3.0.0)
Requires-Dist: pydantic-settings (>=2.4.0,<3.0.0)
Requires-Dist: pymongo (>=4.7.3,<5.0.0) ; extra == "mongo"
Requires-Dist: qdrant-client (>=1.12.1,<2.0.0) ; extra == "qdrant"
Requires-Dist: redis (>=6.2.0,<7.0.0) ; extra == "redis"
Requires-Dist: redisvl (>=0.8.0,<0.9.0) ; extra == "redis"
Requires-Dist: requests (>=2.31,<3.0)
Requires-Dist: rich (!=14.0.0)
Requires-Dist: sentence-transformers (>=5.0.0,<6.0.0)
Requires-Dist: setuptools (>=70.1.1,<81.0.0) ; python_version >= "3.12"
Requires-Dist: structlog (!=25.4.0,>=24.4,<26.0)
Requires-Dist: topk-sdk (>=0.3.7,<0.5.0) ; extra == "topk"
Requires-Dist: transformers (>=4.51.0,<5.0.0) ; extra == "interactive"
Requires-Dist: typing_extensions (>=3.10.0.2)
Requires-Dist: umap-learn (>=0.5.5,<0.6.0) ; extra == "interactive"
